{
	"info": {
		"_postman_id": "a2d4e6a2-948e-48ea-8841-80921020d820",
		"name": "api-lumen",
		"schema": "https://schema.getpostman.com/json/collection/v2.1.0/collection.json"
	},
	"item": [
		{
			"name": "List Players",
			"request": {
				"method": "GET",
				"header": [],
				"url": {
					"raw": "http://localhost:8000/api/v1/players",
					"protocol": "http",
					"host": [
						"localhost"
					],
					"port": "8000",
					"path": [
						"api",
						"v1",
						"players"
					]
				}
			},
			"response": []
		},
		{
			"name": "List Players by ID",
			"protocolProfileBehavior": {
				"disableBodyPruning": true
			},
			"request": {
				"method": "GET",
				"header": [],
				"body": {
					"mode": "urlencoded",
					"urlencoded": []
				},
				"url": {
					"raw": "http://localhost:8000/api/v1/players/1",
					"protocol": "http",
					"host": [
						"localhost"
					],
					"port": "8000",
					"path": [
						"api",
						"v1",
						"players",
						"1"
					]
				}
			},
			"response": []
		},
		{
			"name": "Create a Player",
			"request": {
				"method": "POST",
				"header": [],
				"body": {
					"mode": "raw",
					"raw": "{\r\n    \"name\" : \"Martin Guemes\",\r\n    \"age\" : 28,\r\n    \"nationality\" : \"English\",\r\n    \"club\" : \"Manchester United\",\r\n    \"gender\" : \"Male\"\r\n}",
					"options": {
						"raw": {
							"language": "json"
						}
					}
				},
				"url": {
					"raw": "http://localhost:8000/api/v1/players",
					"protocol": "http",
					"host": [
						"localhost"
					],
					"port": "8000",
					"path": [
						"api",
						"v1",
						"players"
					]
				}
			},
			"response": []
		},
		{
			"name": "Update a specific player",
			"request": {
				"method": "PATCH",
				"header": [],
				"body": {
					"mode": "raw",
					"raw": "{\r\n    \"name\" : \"Martin Guemes\",\r\n    \"age\" : 28,\r\n    \"nationality\" : \"English\",\r\n    \"club\" : \"Manchester United\",\r\n    \"gender\" : \"Male\"\r\n}",
					"options": {
						"raw": {
							"language": "json"
						}
					}
				},
				"url": {
					"raw": "http://localhost:8000/api/v1/players",
					"protocol": "http",
					"host": [
						"localhost"
					],
					"port": "8000",
					"path": [
						"api",
						"v1",
						"players"
					]
				}
			},
			"response": []
		},
		{
			"name": "Delete a specific player",
			"request": {
				"method": "DELETE",
				"header": [],
				"body": {
					"mode": "raw",
					"raw": "{\r\n    \"name\" : \"Martin Miguel de Guemes\",\r\n    \"age\" : 26,\r\n    \"nationality\" : \"English\",\r\n    \"club\" : \"Manchester United\",\r\n    \"gender\" : \"Male\"\r\n}",
					"options": {
						"raw": {
							"language": "json"
						}
					}
				},
				"url": {
					"raw": "http://localhost:8000/api/v1/players/3",
					"protocol": "http",
					"host": [
						"localhost"
					],
					"port": "8000",
					"path": [
						"api",
						"v1",
						"players",
						"3"
					]
				}
			},
			"response": []
		}
	]
}